README.md
setup.py
FloodToolNene.egg-info/PKG-INFO
FloodToolNene.egg-info/SOURCES.txt
FloodToolNene.egg-info/dependency_links.txt
FloodToolNene.egg-info/top_level.txt
flood_tool/__init__.py
flood_tool/analysis.py
flood_tool/geo.py
flood_tool/live.py
flood_tool/mapping.py
flood_tool/tool.py
flood_tool/visual_methods.py